proficient/__init__.py
proficient/client.py
proficient/core/__init__.py
proficient/core/api_error.py
proficient/core/client_wrapper.py
proficient/core/datetime_utils.py
proficient/core/jsonable_encoder.py
proficient/core/remove_none_from_dict.py
proficient/errors/__init__.py
proficient/errors/not_found_error.py
proficient/errors/unprocessable_entity_error.py
proficient/py.typed
proficient/resources/__init__.py
proficient/resources/alerts/__init__.py
proficient/resources/alerts/client.py
proficient/resources/api_keys/__init__.py
proficient/resources/api_keys/client.py
proficient/resources/audit_log/__init__.py
proficient/resources/audit_log/client.py
proficient/resources/connectors/__init__.py
proficient/resources/connectors/client.py
proficient/resources/context_labels/__init__.py
proficient/resources/context_labels/client.py
proficient/resources/dashboard/__init__.py
proficient/resources/dashboard/client.py
proficient/resources/data_access/__init__.py
proficient/resources/data_access/client.py
proficient/resources/data_assets/__init__.py
proficient/resources/data_assets/client.py
proficient/resources/data_classes/__init__.py
proficient/resources/data_classes/client.py
proficient/resources/data_stores/__init__.py
proficient/resources/data_stores/client.py
proficient/resources/export/__init__.py
proficient/resources/export/client.py
proficient/resources/integrations/__init__.py
proficient/resources/integrations/client.py
proficient/resources/policies/__init__.py
proficient/resources/policies/client.py
proficient/resources/roles/__init__.py
proficient/resources/roles/client.py
proficient/resources/sensitivity/__init__.py
proficient/resources/sensitivity/client.py
proficient/resources/users/__init__.py
proficient/resources/users/client.py
proficient/types/__init__.py
proficient/types/access_data_store.py
proficient/types/access_method_accessible_entities_flowchart.py
proficient/types/access_permissions.py
proficient/types/accessible_entities_flowchart_identity_node.py
fern_proficient-0.0.1.dist-info/METADATA
fern_proficient-0.0.1.dist-info/WHEEL
fern_proficient-0.0.1.dist-info/RECORD
